twa/JPSGateway.py
twa/__init__.py
twa/agent/__init__.py
twa/agent/derivation_agent.py
twa/agentlogging/__init__.py
twa/agentlogging/logging.conf
twa/agentlogging/logging.py
twa/conf/__init__.py
twa/conf/agent_conf.py
twa/data_model/__init__.py
twa/data_model/base_ontology.py
twa/data_model/derivation.py
twa/data_model/iris.py
twa/data_model/utils.py
twa/exception/__init__.py
twa/exception/exception.py
twa/kg_operations/__init__.py
twa/kg_operations/derivation_client.py
twa/kg_operations/gateway.py
twa/kg_operations/sparql_client.py
twa/resRegistry/__init__.py
twa/resRegistry/resManager.py
twa/resRegistry/resRegistry.py
twa/resources/__init__.py
twa/resources/resources_registry.json
twa/resources/JpsBaseLib/JpsBaseLib.py
twa/resources/JpsBaseLib/__init__.py
twa/resources/JpsBaseLib/info.txt
twa/resources/JpsBaseLib/jps-base-lib.jar
twa/resources/JpsBaseLib/lib/RoaringBitmap-1.0.0.jar
twa/resources/JpsBaseLib/lib/aopalliance-1.0.jar
twa/resources/JpsBaseLib/lib/apache-jena-libs-4.10.0.pom
twa/resources/JpsBaseLib/lib/apfloat-1.10.1.jar
twa/resources/JpsBaseLib/lib/caffeine-3.1.8.jar
twa/resources/JpsBaseLib/lib/checker-qual-3.42.0.jar
twa/resources/JpsBaseLib/lib/collection-0.7.jar
twa/resources/JpsBaseLib/lib/commons-beanutils-1.9.4.jar
twa/resources/JpsBaseLib/lib/commons-cli-1.5.0.jar
twa/resources/JpsBaseLib/lib/commons-codec-1.16.1.jar
twa/resources/JpsBaseLib/lib/commons-collections-3.2.2.jar
twa/resources/JpsBaseLib/lib/commons-collections4-4.4.jar
twa/resources/JpsBaseLib/lib/commons-compress-1.24.0.jar
twa/resources/JpsBaseLib/lib/commons-csv-1.10.0.jar
twa/resources/JpsBaseLib/lib/commons-digester-2.1.jar
twa/resources/JpsBaseLib/lib/commons-io-2.15.1.jar
twa/resources/JpsBaseLib/lib/commons-lang-2.6.jar
twa/resources/JpsBaseLib/lib/commons-lang3-3.14.0.jar
twa/resources/JpsBaseLib/lib/commons-logging-1.3.0.jar
twa/resources/JpsBaseLib/lib/commons-math3-3.6.1.jar
twa/resources/JpsBaseLib/lib/commons-rdf-api-0.5.0.jar
twa-0.0.9.dist-info/LICENSE
twa-0.0.9.dist-info/METADATA
twa-0.0.9.dist-info/WHEEL
twa-0.0.9.dist-info/entry_points.txt
twa-0.0.9.dist-info/top_level.txt
twa-0.0.9.dist-info/RECORD
