Metadata-Version: 2.1
Name: twa
Version: 0.0.9
Summary: twa is a Python wrapper for TheWorldAvatar project.
Home-page: https://github.com/cambridge-cares/TheWorldAvatar/tree/main/JPS_BASE_LIB/python_wrapper
Author: Jiaru Bai; Daniel Nurkowski
Author-email: jb2197@cam.ac.uk; danieln@cmclinnovations.com
License: MIT
Classifier: License :: OSI Approved :: MIT License
Classifier: Development Status :: 4 - Beta
Classifier: Programming Language :: Python :: 3.8
Classifier: Programming Language :: Python :: 3.9
Classifier: Programming Language :: Python :: 3.10
Requires-Python: >=3.8
License-File: LICENSE
Requires-Dist: py4j (>=0.10.9.1)
Requires-Dist: docopt
Requires-Dist: concurrent-log-handler
Requires-Dist: pydantic
Requires-Dist: rdflib (==7.0.0)
Requires-Dist: requests
Requires-Dist: flask
Requires-Dist: gunicorn (==20.0.4)
Requires-Dist: Flask-APScheduler
Requires-Dist: python-dotenv
Requires-Dist: yagmail
Requires-Dist: Werkzeug
